.class public core104
.super java/lang/Object

.method public <init>()V
  .limit locals 1

  aload_0
  invokespecial java/lang/Object/<init>()V
  return

.end method

.method public static main([Ljava/lang/String;)V
  .limit locals 1
  .limit stack  1

  invokestatic core104/main()I
  pop
  return

.end method


.method public static foo(IIIIIIIIIIIIIIIIIIIIIIIIIIIIIIIIIIIIIIIIIIIIIIIIIIIIIIIIIIIIIIIIIIIIIIIIIIIIIIIIIIIIIIIIIIIIIIIIIIII)I
  .limit locals 100
  .limit stack 3

  nop
  

  ;; return x1 + x2 + x3 + x4 + x5 + x6 + x7 + x8 + x9 + x10 + x11 + x12 + x13 + x14 + x15 + x16 + x17 + x18 + x19 + x20 + x21 + x22 + x23 + x24 + x25 + x26 + x27 + x28 + x29 + x30 + x31 + x32 + x33 + x34 + x35 + x36 + x37 + x38 + x39 + x40 + x41 + x42 + x43 + x44 + x45 + x46 + x47 + x48 + x49 + x50 + x51 + x52 + x53 + x54 + x55 + x56 + x57 + x58 + x59 + x60 + x61 + x62 + x63 + x64 + x65 + x66 + x67 + x68 + x69 + x70 + x71 + x72 + x73 + x74 + x75 + x76 + x77 + x78 + x79 + x80 + x81 + x82 + x83 + x84 + x85 + x86 + x87 + x88 + x89 + x90 + x91 + x92 + x93 + x94 + x95 + x96 + x97 + x98 + x99 + x100;
  
  iload_0  
  iload_1  
  iadd  
  iload_2  
  iadd  
  iload_3  
  iadd  
  iload 4  
  iadd  
  iload 5  
  iadd  
  iload 6  
  iadd  
  iload 7  
  iadd  
  iload 8  
  iadd  
  iload 9  
  iadd  
  iload 10  
  iadd  
  iload 11  
  iadd  
  iload 12  
  iadd  
  iload 13  
  iadd  
  iload 14  
  iadd  
  iload 15  
  iadd  
  iload 16  
  iadd  
  iload 17  
  iadd  
  iload 18  
  iadd  
  iload 19  
  iadd  
  iload 20  
  iadd  
  iload 21  
  iadd  
  iload 22  
  iadd  
  iload 23  
  iadd  
  iload 24  
  iadd  
  iload 25  
  iadd  
  iload 26  
  iadd  
  iload 27  
  iadd  
  iload 28  
  iadd  
  iload 29  
  iadd  
  iload 30  
  iadd  
  iload 31  
  iadd  
  iload 32  
  iadd  
  iload 33  
  iadd  
  iload 34  
  iadd  
  iload 35  
  iadd  
  iload 36  
  iadd  
  iload 37  
  iadd  
  iload 38  
  iadd  
  iload 39  
  iadd  
  iload 40  
  iadd  
  iload 41  
  iadd  
  iload 42  
  iadd  
  iload 43  
  iadd  
  iload 44  
  iadd  
  iload 45  
  iadd  
  iload 46  
  iadd  
  iload 47  
  iadd  
  iload 48  
  iadd  
  iload 49  
  iadd  
  iload 50  
  iadd  
  iload 51  
  iadd  
  iload 52  
  iadd  
  iload 53  
  iadd  
  iload 54  
  iadd  
  iload 55  
  iadd  
  iload 56  
  iadd  
  iload 57  
  iadd  
  iload 58  
  iadd  
  iload 59  
  iadd  
  iload 60  
  iadd  
  iload 61  
  iadd  
  iload 62  
  iadd  
  iload 63  
  iadd  
  iload 64  
  iadd  
  iload 65  
  iadd  
  iload 66  
  iadd  
  iload 67  
  iadd  
  iload 68  
  iadd  
  iload 69  
  iadd  
  iload 70  
  iadd  
  iload 71  
  iadd  
  iload 72  
  iadd  
  iload 73  
  iadd  
  iload 74  
  iadd  
  iload 75  
  iadd  
  iload 76  
  iadd  
  iload 77  
  iadd  
  iload 78  
  iadd  
  iload 79  
  iadd  
  iload 80  
  iadd  
  iload 81  
  iadd  
  iload 82  
  iadd  
  iload 83  
  iadd  
  iload 84  
  iadd  
  iload 85  
  iadd  
  iload 86  
  iadd  
  iload 87  
  iadd  
  iload 88  
  iadd  
  iload 89  
  iadd  
  iload 90  
  iadd  
  iload 91  
  iadd  
  iload 92  
  iadd  
  iload 93  
  iadd  
  iload 94  
  iadd  
  iload 95  
  iadd  
  iload 96  
  iadd  
  iload 97  
  iadd  
  iload 98  
  iadd  
  iload 99  
  iadd  
  ireturn
  return

.end method

.method public static main()I
  .limit locals 2
  .limit stack 102

  nop
  

  ;; int x;
  

  ;; Reserve address 0 for x. No code generated.  

  ;; x = foo (1, 2, 3, 4, 5, 6, 7, 8, 9, 10, 11, 12, 13, 14, 15, 16, 17, 18, 19, 20, 21, 22, 23, 24, 25, 26, 27, 28, 29, 30, 31, 32, 33, 34, 35, 36, 37, 38, 39, 40, 41, 42, 43, 44, 45, 46, 47, 48, 49, 50, 51, 52, 53, 54, 55, 56, 57, 58, 59, 60, 61, 62, 63, 64, 65, 66, 67, 68, 69, 70, 71, 72, 73, 74, 75, 76, 77, 78, 79, 80, 81, 82, 83, 84, 85, 86, 87, 88, 89, 90, 91, 92, 93, 94, 95, 96, 97, 98, 99, 100);
  
  iconst_1  
  iconst_2  
  iconst_3  
  iconst_4  
  iconst_5  
  bipush 6  
  bipush 7  
  bipush 8  
  bipush 9  
  bipush 10  
  bipush 11  
  bipush 12  
  bipush 13  
  bipush 14  
  bipush 15  
  bipush 16  
  bipush 17  
  bipush 18  
  bipush 19  
  bipush 20  
  bipush 21  
  bipush 22  
  bipush 23  
  bipush 24  
  bipush 25  
  bipush 26  
  bipush 27  
  bipush 28  
  bipush 29  
  bipush 30  
  bipush 31  
  bipush 32  
  bipush 33  
  bipush 34  
  bipush 35  
  bipush 36  
  bipush 37  
  bipush 38  
  bipush 39  
  bipush 40  
  bipush 41  
  bipush 42  
  bipush 43  
  bipush 44  
  bipush 45  
  bipush 46  
  bipush 47  
  bipush 48  
  bipush 49  
  bipush 50  
  bipush 51  
  bipush 52  
  bipush 53  
  bipush 54  
  bipush 55  
  bipush 56  
  bipush 57  
  bipush 58  
  bipush 59  
  bipush 60  
  bipush 61  
  bipush 62  
  bipush 63  
  bipush 64  
  bipush 65  
  bipush 66  
  bipush 67  
  bipush 68  
  bipush 69  
  bipush 70  
  bipush 71  
  bipush 72  
  bipush 73  
  bipush 74  
  bipush 75  
  bipush 76  
  bipush 77  
  bipush 78  
  bipush 79  
  bipush 80  
  bipush 81  
  bipush 82  
  bipush 83  
  bipush 84  
  bipush 85  
  bipush 86  
  bipush 87  
  bipush 88  
  bipush 89  
  bipush 90  
  bipush 91  
  bipush 92  
  bipush 93  
  bipush 94  
  bipush 95  
  bipush 96  
  bipush 97  
  bipush 98  
  bipush 99  
  bipush 100  
  invokestatic core104/foo(IIIIIIIIIIIIIIIIIIIIIIIIIIIIIIIIIIIIIIIIIIIIIIIIIIIIIIIIIIIIIIIIIIIIIIIIIIIIIIIIIIIIIIIIIIIIIIIIIIII)I  
  istore_0  
  iload_0  
  pop  

  ;; printInt (x);
  
  iload_0  
  invokestatic Runtime/printInt(I)V    

  ;; return x;
  
  iload_0  
  ireturn
  return

.end method
